nqlib/__init__.py
nqlib/linalg.py
nqlib/quantizer.py
nqlib/system_description.py
nqlib/types.py
nqlib-1.0.0.dist-info/licenses/LICENSE.txt
nqlib-1.0.0.dist-info/METADATA
nqlib-1.0.0.dist-info/WHEEL
nqlib-1.0.0.dist-info/top_level.txt
nqlib-1.0.0.dist-info/RECORD
