Metadata-Version: 2.4
Name: nqlib
Version: 1.0.0
Summary: NQLib: Library to design noise shaping quantizer for discrete-valued input control.
Author: knttnk
Project-URL: Homepage, https://github.com/knttnk/NQLib
Keywords: discrete-valued input control,control theory,quantizer,control system design,quantization,simulation
Classifier: Programming Language :: Python :: 3
Classifier: License :: OSI Approved :: MIT License
Classifier: Operating System :: OS Independent
Requires-Python: >=3.11
License-File: LICENSE.txt
Requires-Dist: numpy
Requires-Dist: scipy>=1.10.1
Requires-Dist: slycot
Requires-Dist: control
Requires-Dist: cvxpy
Dynamic: license-file
